odoo/addons/product_packaging_archive/README.rst
odoo/addons/product_packaging_archive/__init__.py
odoo/addons/product_packaging_archive/__manifest__.py
odoo/addons/product_packaging_archive/i18n/it.po
odoo/addons/product_packaging_archive/i18n/product_packaging_archive.pot
odoo/addons/product_packaging_archive/models/__init__.py
odoo/addons/product_packaging_archive/models/product_packaging.py
odoo/addons/product_packaging_archive/readme/CONTRIBUTORS.md
odoo/addons/product_packaging_archive/readme/DESCRIPTION.md
odoo/addons/product_packaging_archive/static/description/icon.png
odoo/addons/product_packaging_archive/static/description/index.html
odoo/addons/product_packaging_archive/tests/__init__.py
odoo/addons/product_packaging_archive/tests/test_product_packaging_archive.py
odoo/addons/product_packaging_archive/views/product_packaging.xml
odoo_addon_product_packaging_archive-18.0.1.0.0.4.dist-info/METADATA
odoo_addon_product_packaging_archive-18.0.1.0.0.4.dist-info/WHEEL
odoo_addon_product_packaging_archive-18.0.1.0.0.4.dist-info/top_level.txt
odoo_addon_product_packaging_archive-18.0.1.0.0.4.dist-info/RECORD
